{
  "displayName": "Remote debugging should be turned off for Function Apps",
  "policyType": "BuiltIn",
  "mode": "Indexed",
  "description": "Remote debugging requires inbound ports to be opened on function apps. Remote debugging should be turned off.",
  "metadata": {
    "version": "1.0.0",
    "category": "App Service"
  },
  "parameters": {
    "effect": {
      "type": "String",
      "metadata": {
        "displayName": "Effect",
        "description": "Enable or disable the execution of the policy"
      },
      "allowedValues": [
        "AuditIfNotExists",
        "Disabled"
      ],
      "defaultValue": "AuditIfNotExists"
    }
  },
  "policyRule": {
    "if": {
      "allOf": [
        {
          "field": "type",
          "equals": "Microsoft.Web/sites"
        },
        {
          "field": "kind",
          "like": "functionapp*"
        }
      ]
    },
    "then": {
      "effect": "[parameters('effect')]",
      "details": {
        "type": "Microsoft.Web/sites/config",
        "existenceCondition": {
          "field": "Microsoft.Web/sites/config/web.remoteDebuggingEnabled",
          "equals": "false"
        }
      }
    }
  }
}

