{
  "roleName": "AgFood Platform Service Contributor",
  "type": "BuiltInRole",
  "description": "Provides contribute access to AgFood Platform Service",
  "assignableScopes": [
    "/"
  ],
  "permissions": [
    {
      "actions": [],
      "notActions": [],
      "dataActions": [
        "Microsoft.AgFoodPlatform/*/action",
        "Microsoft.AgFoodPlatform/*/read",
        "Microsoft.AgFoodPlatform/*/write"
      ],
      "notDataActions": [
        "Microsoft.AgFoodPlatform/farmers/write",
        "Microsoft.AgFoodPlatform/deletionJobs/*/write"
      ]
    }
  ],
  "createdOn": "2020-09-14T10:21:09.7239169Z",
  "updatedOn": "2021-07-19T05:45:17.7691871Z",
  "createdBy": null,
  "updatedBy": null
}

